{
    "menuName": "ProjectOutordCompnay",
    "queryId": "projectMapper.retrieveOutordEntrpsList",
    "keyColumn": "outordEntrpsId",
    "tableColumns": [
        { "key": "outordEntrpsNm", "value": "업체명", "alignment": "center" },
        { "key": "brno", "value": "사업자등록번호", "alignment": "center", "width": "15%" },
        { "key": "picFlnm", "value": "담당자", "alignment": "center", "width": "10%" },
        { "key": "telno", "value": "전화번호", "alignment": "center", "width": "15%" },
        { "key": "addr", "value": "주소", "alignment": "center" },
        { "key": "fileNm", "value": "과거 참여프로젝트", "alignment": "center" },
        { "value": "삭제",  "button": {"text" : "삭제"},"alignment": "center" , "width": "8%"}
    ],
    "searchInfo": {
        "searchParams": {
        },
        "textBoxItem": [
            {
                "placeholder": "업체명",
                "name": "outordEntrpsNm"
            },
            {
                "placeholder": "전화번호",
                "name": "telno"
            },
            {
                "placeholder": "담당자",
                "name": "picFlnm"
            }
        ]
    }
}